llm_commit_generator/__init__.py
llm_commit_generator/__main__.py
llm_commit_generator/ai_service.py
llm_commit_generator/cli.py
llm_commit_generator/commit_generator.py
llm_commit_generator/prompts.py
llm_commit_generator-0.1.3.dist-info/licenses/LICENSE
llm_commit_generator-0.1.3.dist-info/METADATA
llm_commit_generator-0.1.3.dist-info/WHEEL
llm_commit_generator-0.1.3.dist-info/entry_points.txt
llm_commit_generator-0.1.3.dist-info/top_level.txt
llm_commit_generator-0.1.3.dist-info/RECORD
