Metadata-Version: 2.4
Name: llm-commit-generator
Version: 0.1.3
License: Apache-2.0
Project-URL: Documentation, https://tooluse.github.io/llmcommit/
Project-URL: Issues, https://github.com/tooluse/llmcommit/issues
Project-URL: Source, https://github.com/tooluse/llmcommit
Requires-Python: >=3.10
License-File: LICENSE
Requires-Dist: loguru
Requires-Dist: requests
Provides-Extra: docs
Requires-Dist: mkdocs; extra == "docs"
Requires-Dist: mkdocs-material; extra == "docs"
Requires-Dist: mkdocstrings-python; extra == "docs"
Provides-Extra: tests
Requires-Dist: pytest<9,>=8; extra == "tests"
Requires-Dist: pytest-sugar>=0.9.6; extra == "tests"
Dynamic: license-file
